screwdrivercd/changelog/__init__.py
screwdrivercd/changelog/__main__.py
screwdrivercd/changelog/generate.py
screwdrivercd/documentation/__init__.py
screwdrivercd/documentation/__main__.py
screwdrivercd/documentation/cli.py
screwdrivercd/documentation/exceptions.py
screwdrivercd/documentation/plugin.py
screwdrivercd/documentation/utility.py
screwdrivercd/documentation/mkdocs/__init__.py
screwdrivercd/documentation/mkdocs/plugin.py
screwdrivercd/documentation/sphinx/__init__.py
screwdrivercd/documentation/sphinx/plugin.py
screwdrivercd/installdeps/__init__.py
screwdrivercd/installdeps/__main__.py
screwdrivercd/installdeps/cli.py
screwdrivercd/installdeps/config.py
screwdrivercd/installdeps/installer.py
screwdrivercd/installdeps/requirement.py
screwdrivercd/installdeps/installers/__init__.py
screwdrivercd/installdeps/installers/apk.py
screwdrivercd/installdeps/installers/apt.py
screwdrivercd/installdeps/installers/brew.py
screwdrivercd/installdeps/installers/pip3.py
screwdrivercd/installdeps/installers/yum.py
screwdrivercd/packaging/__init__.py
screwdrivercd/packaging/build_python.py
screwdrivercd/packaging/publish_python.py
screwdrivercd/packaging/python.py
screwdrivercd/repo/__init__.py
screwdrivercd/repo/release.py
screwdrivercd/screwdriver/__init__.py
screwdrivercd/screwdriver/environment.py
screwdrivercd/screwdriver/github_deploykey.py
screwdrivercd/screwdriver/metadata.py
screwdrivercd/screwdriver/templates/__init__.py
screwdrivercd/utility/__init__.py
screwdrivercd/utility/contextmanagers.py
screwdrivercd/utility/environment.py
screwdrivercd/utility/exceptions.py
screwdrivercd/utility/output.py
screwdrivercd/utility/package.py
screwdrivercd/utility/run.py
screwdrivercd/utility/screwdriver.py
screwdrivercd/utility/tox.py
screwdrivercd/validation/__init__.py
screwdrivercd/validation/validate_dependencies.py
screwdrivercd/validation/validate_package_quality.py
screwdrivercd/validation/validate_style.py
screwdrivercd/validation/validate_type.py
screwdrivercd-2.2.967077.dist-info/LICENSE
screwdrivercd-2.2.967077.dist-info/METADATA
screwdrivercd-2.2.967077.dist-info/WHEEL
screwdrivercd-2.2.967077.dist-info/entry_points.txt
screwdrivercd-2.2.967077.dist-info/top_level.txt
screwdrivercd-2.2.967077.dist-info/zip-safe
screwdrivercd-2.2.967077.dist-info/RECORD
