Metadata-Version: 2.1
Name: screwdrivercd
Version: 2.2.967077
Summary: Python helper utilities for screwdriver CI/CD
Home-page: https://github.com/yahoo/python-screwdrivercd
Author: Yahoo Python Platform Team
Author-email: python@yahooinc.com
Project-URL: Documentation, https://yahoo.github.io/python-screwdrivercd/
Project-URL: Source, https://github.com/yahoo/python-screwdrivercd
Project-URL: Change Log, https://yahoo.github.io/python-screwdrivercd/changelog/
Project-URL: CI Pipeline, https://cd.screwdriver.cd/pipelines/3063
Keywords: ci,cd,screwdriver
Classifier: Development Status :: 5 - Production/Stable
Classifier: Intended Audience :: Developers
Classifier: License :: OSI Approved :: Apache Software License
Classifier: Programming Language :: Python :: 3 :: Only
Classifier: Programming Language :: Python :: 3.8
Classifier: Programming Language :: Python :: 3.9
Classifier: Programming Language :: Python :: 3.10
Classifier: Programming Language :: Python :: 3.11
Classifier: Programming Language :: Python :: 3.12
Requires-Python: >=3.11
License-File: LICENSE
Requires-Dist: distro
Requires-Dist: lxml>=4.9.1
Requires-Dist: mkdocs
Requires-Dist: mypy
Requires-Dist: packaging
Requires-Dist: parsley
Requires-Dist: pycodestyle>=2.3.1
Requires-Dist: pypirun
Requires-Dist: pyroma
Requires-Dist: requests
Requires-Dist: sphinx!=1.8.0
Requires-Dist: termcolor
Requires-Dist: tomlkit
Requires-Dist: twine
Requires-Dist: wheel
Provides-Extra: documentation
Requires-Dist: markdown; extra == "documentation"
Requires-Dist: pymdown-extensions; extra == "documentation"
Requires-Dist: markdown-include; extra == "documentation"
Requires-Dist: mkdocs-bootstrap4; extra == "documentation"
Requires-Dist: mkdocs-cinder; extra == "documentation"
Requires-Dist: mkdocs-material; extra == "documentation"
Requires-Dist: pygments; extra == "documentation"
Requires-Dist: recommonmark; extra == "documentation"
Provides-Extra: doc-build
Requires-Dist: markdown; extra == "doc-build"
Requires-Dist: pymdown-extensions; extra == "doc-build"
Requires-Dist: markdown-include; extra == "doc-build"
Requires-Dist: mkdocs-bootstrap4; extra == "doc-build"
Requires-Dist: mkdocs-material; extra == "doc-build"
Requires-Dist: pygments; extra == "doc-build"
Requires-Dist: recommonmark; extra == "doc-build"
Provides-Extra: test
Requires-Dist: pytest; extra == "test"
Requires-Dist: pytest-cov; extra == "test"
Requires-Dist: pypirun; extra == "test"
Requires-Dist: vcrpy-unittest; extra == "test"
